Metadata-Version: 1.1
Name: vibes
Version: 0.2.2
Summary: python Api for VIbes (VIsualizer for Intervals and Boxes)
Home-page: http://enstabretagnerobotics.github.io/VIBES/
Author: EnstaRobotics
Author-email: ben.ensta@gmail.com
License: LGPLv3
Keywords: VIbes,Interval Arithmetics,Graphics Tools
Platform: UNKNOWN
Classifier: Development Status :: 5 - Production/Stable
Classifier: Topic :: Utilities
Classifier: Topic :: Scientific/Engineering :: Visualization
Classifier: Operating System :: OS Independent
Classifier: License :: OSI Approved :: GNU General Public License v3 or later (GPLv3+)
